<?xml version="1.0" encoding="UTF-8" standalone="no"?>
<configuration version="1.0.7.16">
  <General>
    <HarmonyPath path="../../../microchip/harmony/v1_07_01"/>
    <ForceOptimization flag="true"/>
  </General>
  <Manifest>
    <Files>
      <File>
        <Name>semphr.h</Name>
        <Path>Header Files/FreeRTOS</Path>
      </File>
      <File>
        <Name>list.c</Name>
        <Path>Source Files/FreeRTOS</Path>
      </File>
      <File>
        <Name>drv_tmr.h</Name>
        <Path>Header Files/framework/driver/tmr</Path>
      </File>
      <File>
        <Name>sys_devcon.c</Name>
        <Path>Source Files/framework/system/devcon/src</Path>
      </File>
      <File>
        <Name>drv_i2c_bb.h</Name>
        <Path>Header Files/framework/driver/i2c</Path>
      </File>
      <File>
        <Name>queue.h</Name>
        <Path>Header Files/FreeRTOS</Path>
      </File>
      <File>
        <Name>sys_tmr.h</Name>
        <Path>Header Files/framework/system/tmr</Path>
      </File>
      <File>
        <Name>sys_tmr.c</Name>
        <Path>Source Files/framework/system/tmr/src</Path>
      </File>
      <File>
        <Name>croutine.c</Name>
        <Path>Source Files/FreeRTOS</Path>
      </File>
      <File>
        <Name>StackMacros.h</Name>
        <Path>Header Files/FreeRTOS</Path>
      </File>
      <File>
        <Name>osal_freertos.c</Name>
        <Path>Source Files/framework/osal/src</Path>
      </File>
      <File>
        <Name>tasks.c</Name>
        <Path>Source Files/FreeRTOS</Path>
      </File>
      <File>
        <Name>sys_ports.h</Name>
        <Path>Header Files/framework/system/ports</Path>
      </File>
      <File>
        <Name>portmacro.h</Name>
        <Path>Header Files/FreeRTOS/portable/MPLAB/PIC32MZ</Path>
      </File>
      <File>
        <Name>projdefs.h</Name>
        <Path>Header Files/FreeRTOS</Path>
      </File>
      <File>
        <Name>ISR_Support.h</Name>
        <Path>Header Files/FreeRTOS/portable/MPLAB/PIC32MZ</Path>
      </File>
      <File>
        <Name>portable.h</Name>
        <Path>Header Files/FreeRTOS</Path>
      </File>
      <File>
        <Name>croutine.h</Name>
        <Path>Header Files/FreeRTOS</Path>
      </File>
      <File>
        <Name>list.h</Name>
        <Path>Header Files/FreeRTOS</Path>
      </File>
      <File>
        <Name>driver.h</Name>
        <Path>Header Files/framework/driver</Path>
      </File>
      <File>
        <Name>sys_common.h</Name>
        <Path>Header Files/framework/system/common</Path>
      </File>
      <File>
        <Name>sys_int_pic32.c</Name>
        <Path>Source Files/framework/system/int/src</Path>
      </File>
      <File>
        <Name>event_groups.h</Name>
        <Path>Header Files/FreeRTOS</Path>
      </File>
      <File>
        <Name>drv_i2c_bb_a.c</Name>
        <Path>Source Files/framework/driver/i2c/src/dynamic</Path>
      </File>
      <File>
        <Name>bsp_config.h</Name>
        <Path>Header Files/bsp/chipkit_wifire</Path>
      </File>
      <File>
        <Name>drv_i2c_bb.c</Name>
        <Path>Source Files/framework/driver/i2c/src/dynamic</Path>
      </File>
      <File>
        <Name>sys_devcon_cache_pic32mz.S</Name>
        <Path>Source Files/framework/system/devcon/src</Path>
      </File>
      <File>
        <Name>drv_tmr.c</Name>
        <Path>Source Files/framework/driver/tmr/src/dynamic</Path>
      </File>
      <File>
        <Name>FreeRTOS.h</Name>
        <Path>Header Files/FreeRTOS</Path>
      </File>
      <File>
        <Name>sys_devcon_cache.h</Name>
        <Path>Header Files/framework/system/devcon</Path>
      </File>
      <File>
        <Name>sys_ports.c</Name>
        <Path>Source Files/framework/system/ports/src</Path>
      </File>
      <File>
        <Name>sys_devcon.h</Name>
        <Path>Header Files/framework/system/devcon</Path>
      </File>
      <File>
        <Name>event_groups.c</Name>
        <Path>Source Files/FreeRTOS</Path>
      </File>
      <File>
        <Name>system.h</Name>
        <Path>Header Files/framework/system</Path>
      </File>
      <File>
        <Name>bsp_sys_init.c</Name>
        <Path>Source Files/bsp/chipkit_wifire</Path>
      </File>
      <File>
        <Name>port_asm.S</Name>
        <Path>Source Files/FreeRTOS/portable/MPLAB/PIC32MZ</Path>
      </File>
      <File>
        <Name>sys_module.h</Name>
        <Path>Header Files/framework/system/common</Path>
      </File>
      <File>
        <Name>sys_devcon_pic32mz.c</Name>
        <Path>Source Files/framework/system/devcon/src</Path>
      </File>
      <File>
        <Name>drv_i2c_bb_a.h</Name>
        <Path>Header Files/framework/driver/i2c</Path>
      </File>
      <File>
        <Name>timers.h</Name>
        <Path>Header Files/FreeRTOS</Path>
      </File>
      <File>
        <Name>timers.c</Name>
        <Path>Source Files/FreeRTOS</Path>
      </File>
      <File>
        <Name>task.h</Name>
        <Path>Header Files/FreeRTOS</Path>
      </File>
      <File>
        <Name>heap_2.c</Name>
        <Path>Source Files/FreeRTOS/portable/MemMang</Path>
      </File>
      <File>
        <Name>mpu_wrappers.h</Name>
        <Path>Header Files/FreeRTOS</Path>
      </File>
      <File>
        <Name>port.c</Name>
        <Path>Source Files/FreeRTOS/portable/MPLAB/PIC32MZ</Path>
      </File>
      <File>
        <Name>queue.c</Name>
        <Path>Source Files/FreeRTOS</Path>
      </File>
      <File>
        <Name>sys_int.h</Name>
        <Path>Header Files/framework/system/int</Path>
      </File>
    </Files>
    <Templates>
      <Template>
        <Name>sys_ports_static.c</Name>
        <Path>Source Files/app/system_config/default/framework/system/ports/src</Path>
        <Checksum>6F3B156DAB2894754C58A97B09ECD13E</Checksum>
      </Template>
      <Template>
        <Name>system_init.c</Name>
        <Path>Source Files/app/system_config/default</Path>
        <Checksum>B325ACD255754EE1C565F4DFF8670009</Checksum>
      </Template>
      <Template>
        <Name>main.c</Name>
        <Path>Source Files/app</Path>
        <Checksum>81A51474D8A80D41AD749DEAE4C1A7A3</Checksum>
      </Template>
      <Template>
        <Name>system_interrupt_a.S</Name>
        <Path>Source Files/app/system_config/default</Path>
        <Checksum>66DBFDC7197A4E493BCA34C9EF548090</Checksum>
      </Template>
      <Template>
        <Name>global_event.h</Name>
        <Path>Header Files/app</Path>
        <Checksum>25F68F89A821B204B3B2BE9F493DEE02</Checksum>
      </Template>
      <Template>
        <Name>system_definitions.h</Name>
        <Path>Header Files/app/system_config/default</Path>
        <Checksum>9CF05973572975936CC8A00D560DCE0A</Checksum>
      </Template>
      <Template>
        <Name>system_exceptions.c</Name>
        <Path>Source Files/app/system_config/default</Path>
        <Checksum>C111969CA43D6CEA1E9E33A6164E7AE0</Checksum>
        <ProjectFileChecksum>137B7AF2389C618C34FBE452D9E62EF8</ProjectFileChecksum>
      </Template>
      <Template>
        <Name>flir.c</Name>
        <Path>Source Files/app</Path>
        <Checksum>30AF2BA15F014AE93E6B087D79ECDF75</Checksum>
        <ProjectFileChecksum>5517A870A806891BD9A654A3C7436958</ProjectFileChecksum>
      </Template>
      <Template>
        <Name>global_event.c</Name>
        <Path>Source Files/app</Path>
        <Checksum>D2E55E3D097D44D37CEBD4D6CB2B05CE</Checksum>
      </Template>
      <Template>
        <Name>FreeRTOSConfig.h</Name>
        <Path>Header Files/app/system_config/default</Path>
        <Checksum>CBCCFD050FCC0AF8456A05508CFA98E8</Checksum>
      </Template>
      <Template>
        <Name>system_tasks.c</Name>
        <Path>Source Files/app/system_config/default</Path>
        <Checksum>5A64BFAB36C32516C97B02493C484C9C</Checksum>
        <ProjectFileChecksum>8CEC43682CFD0A8D495EFE425A2DF262</ProjectFileChecksum>
      </Template>
      <Template>
        <Name>flir.h</Name>
        <Path>Header Files/app</Path>
        <Checksum>6122A149C059A40827F0BF6A003CEF39</Checksum>
        <ProjectFileChecksum>DF3C006B41DFD7FC8AA311503F36FA1F</ProjectFileChecksum>
      </Template>
      <Template>
        <Name>system_config.h</Name>
        <Path>Header Files/app/system_config/default</Path>
        <Checksum>B051ACFE0D4E438BA94709E6BF6281F4</Checksum>
      </Template>
      <Template>
        <Name>sys_clk_static.h</Name>
        <Path>Header Files/app/system_config/default/framework/system/clk</Path>
        <Checksum>B4BD59D8D7C4DA95DC5E3B57755FD352</Checksum>
      </Template>
      <Template>
        <Name>system_interrupt.c</Name>
        <Path>Source Files/app/system_config/default</Path>
        <Checksum>364EBBFC706E2418E360943624063EC2</Checksum>
      </Template>
      <Template>
        <Name>rtos_hooks.c</Name>
        <Path>Source Files/app/system_config/default</Path>
        <Checksum>FA52743264536E5207D2ADBE57B48D05</Checksum>
      </Template>
      <Template>
        <Name>sys_clk_static.c</Name>
        <Path>Source Files/app/system_config/default/framework/system/clk/src</Path>
        <Checksum>4681B98AC85858FD3FFA130908EDA5D0</Checksum>
      </Template>
    </Templates>
    <CompilerItems>
      <C32-AS>
        <Include value="../../../../../microchip/harmony/v1_07_01/third_party/rtos/FreeRTOS/Source/portable/MPLAB/PIC32MZ"/>
        <Include value="../../../../../microchip/harmony/v1_07_01/third_party/rtos/FreeRTOS/Source/include"/>
        <Include value="../src/system_config/default"/>
      </C32-AS>
      <C32>
        <Include value="../../../../../microchip/harmony/v1_07_01/bsp/chipkit_wifire"/>
        <Include value="../../../../../microchip/harmony/v1_07_01/third_party/rtos/FreeRTOS/Source/portable/MPLAB/PIC32MZ"/>
        <Include value="../../../../../microchip/harmony/v1_07_01/third_party/rtos/FreeRTOS/Source/include"/>
        <Include value="../src/system_config/default"/>
      </C32>
    </CompilerItems>
    <Libraries>
      <Library value="../../../../../microchip/harmony/v1_07_01/bin/framework/peripheral/PIC32MZ2048EFG100_peripherals.a"/>
    </Libraries>
  </Manifest>
</configuration>
